{"p":"","i":"https://enviotodo.lacomuna.mx/wp-content/uploads/2018/07/Biberones-Dr-Brown-125x125.jpg","pd":"07/07/2018","mdf":"07/09/2018","mt":[{"_edit_lock":["1533064747:1"],"_edit_last":["10"],"_thumbnail_id":["2436"],"_yoast_wpseo_primary_category":["479"],"producto_categoria":["Biberones para beb\u00e9."],"producto_caracteristica":["Ayudan a alimentar a tu beb\u00e9 c\u00f3modamente y sin c\u00f3licos."],"producto_lineas":["Est\u00e1ndar, cuello ancho y vidrio."],"producto_presentaciones":["Caja con 1 biber\u00f3n, Set de 2 y 3 biberones."],"_yoast_wpseo_focuskw_text_input":["Biberones Dr Brown"],"_yoast_wpseo_focuskw":["Biberones Dr Brown"],"_yoast_wpseo_linkdex":["88"],"_yoast_wpseo_content_score":["90"],"_oembed_5d83844ac08f5782b23363482f479ab8":["{{unknown}}"]}],"c":"","md":[],"rl":[{"ID":9640,"post_title":"Tommee Tippee","post_name":"tommee-tippee","post_parent":0},{"ID":9582,"post_title":"Capent","post_name":"capent","post_parent":0},{"ID":9315,"post_title":"Pasta Lassar","post_name":"pasta-lassar","post_parent":0},{"ID":9329,"post_title":"Hipoglos","post_name":"hipoglos","post_parent":0},{"ID":7903,"post_title":"Tira Leche","post_name":"tira-leche","post_parent":0},{"ID":7901,"post_title":"Mustela Crema","post_name":"mustela-crema","post_parent":0},{"ID":7442,"post_title":"Evenflo","post_name":"evenflo","post_parent":0},{"ID":7288,"post_title":"Avent","post_name":"avent","post_parent":0}]}