{"p":"1","i":"https://enviotodo.lacomuna.mx/wp-content/uploads/2018/02/ASA-125x125.jpg","pd":"02/13/2018","mdf":"02/13/2018","mt":[{"_edit_lock":["1518556319:3"],"_edit_last":["3"],"_yoast_wpseo_primary_category":["324"],"quefarma_med_tipo":["Medicamento de Patente."],"quefarma_med_formula":["\u00c1cido Acetilsalic\u00edlico."],"quefarma_med_presentaciones":["100 mg \/ 500 mg."],"quefarma_med_administracion":["Oral."],"quefarma_med_venta":["Sin receta."],"_yoast_wpseo_focuskw_text_input":["ASA"],"_yoast_wpseo_focuskw":["ASA"],"_yoast_wpseo_linkdex":["90"],"_yoast_wpseo_content_score":["90"],"_thumbnail_id":["1287"],"med_riesgo_embarazo":["alto"],"med_riesgo_lactancia":["bajo"]}],"c":"artritis,catarro o resfriado,desinflamar,dolor de articulaciones,dolor de cabeza,dolor de garganta,dolor de huesos,dolor de muelas,dolor de oído,dolores musculares,fiebre,gripa,migraña,prevenir infartos,problemas de circulación,reumas","md":[]}