{"p":"108","i":"https://enviotodo.lacomuna.mx/wp-content/uploads/2018/11/ossopan-1-125x125.jpg","pd":"11/13/2018","mdf":"02/25/2020","mt":[{"_edit_lock":["1582669856:14"],"_edit_last":["14"],"_thumbnail_id":["3761"],"_yoast_wpseo_primary_category":["217"],"quefarma_med_tipo":["Medicamento Mineral de Patente"],"quefarma_med_formula":["Complejo ose\u00ednico mineral al 100%"],"quefarma_med_presentaciones":["Tabletas \/ Sobres de polvo"],"quefarma_med_administracion":["Oral"],"quefarma_med_venta":["Con receta"],"_yoast_wpseo_focuskw":["ossopan"],"_yoast_wpseo_linkdex":["78"],"_yoast_wpseo_content_score":["90"],"med_guias_enlaces_que_sirve":[""],"med_guias_enlaces_presentaciones":[""],"med_guias_enlaces_dosis":[""],"med_guias_enlaces_efectos":[""],"med_guias_enlaces_compara_precio":[""],"med_doctor_resp":[""],"med_riesgo_embarazo":["bajo"],"med_riesgo_lactancia":["bajo"],"med_riesgo_alcohol":["medio"],"quefarma_med_para_que_es":["Tratar la deficiencia de calcio"],"med_patente_generico":["patente"],"med_con_sin_receta":["con_receta"]}],"c":"fracturas,osteoporosis","md":[],"rl":[{"ID":9659,"post_title":"Prolia","post_name":"prolia","post_parent":0},{"ID":9516,"post_title":"Ketorolaco y Tramadol","post_name":"ketorolaco-y-tramadol","post_parent":0},{"ID":9144,"post_title":"Malival Compuesto","post_name":"malival-compuesto","post_parent":0},{"ID":8466,"post_title":"Alin Depot","post_name":"alin-depot","post_parent":0},{"ID":7908,"post_title":"Wobenzym","post_name":"wobenzym","post_parent":0},{"ID":8050,"post_title":"Dafloxen","post_name":"dafloxen","post_parent":0},{"ID":7645,"post_title":"Facicam","post_name":"facicam","post_parent":0},{"ID":7280,"post_title":"X-Ray","post_name":"x-ray","post_parent":0}]}