{"p":"403","i":"https://enviotodo.lacomuna.mx/wp-content/uploads/2019/01/duphaston-10mg-caja-con-20-tabletas-125x125.jpg","pd":"01/19/2019","mdf":"02/22/2020","mt":[{"_edit_lock":["1582745150:7"],"_edit_last":["14"],"_yoast_wpseo_primary_category":["411"],"quefarma_med_tipo":["Medicamento Hormonal de Patente"],"quefarma_med_formula":["Didrogesterona al 100%"],"quefarma_med_presentaciones":["Tabletas"],"quefarma_med_administracion":["Oral"],"quefarma_med_venta":["Con receta"],"_yoast_wpseo_content_score":["90"],"_thumbnail_id":["4351"],"_yoast_wpseo_focuskw":["Duphaston"],"_yoast_wpseo_linkdex":["78"],"med_guias_enlaces_que_sirve":[""],"med_guias_enlaces_presentaciones":[""],"med_guias_enlaces_dosis":[""],"med_guias_enlaces_efectos":[""],"med_guias_enlaces_compara_precio":[""],"med_doctor_resp":[""],"med_riesgo_embarazo":["bajo"],"med_riesgo_lactancia":["alto"],"med_riesgo_alcohol":["alto"],"quefarma_med_para_que_es":["Tratar la deficiencia de progesterona"],"med_patente_generico":["patente"],"med_con_sin_receta":["con_receta"]}],"c":"ayuda en el embarazo,cólicos menstruales,hemorragias,menopausia,regular hormonas femeninas","md":[]}