{"p":"272","i":"https://enviotodo.lacomuna.mx/wp-content/uploads/2019/04/7501122960317_11-125x125.jpg","pd":"04/14/2019","mdf":"02/26/2020","mt":[{"_edit_lock":["1582827389:7"],"_edit_last":["14"],"_yoast_wpseo_primary_category":["677"],"quefarma_med_tipo":["Medicamento antiinflamatorio y antipruriginoso de Patente"],"quefarma_med_formula":["Clobetasol al 100%"],"quefarma_med_presentaciones":["Crema"],"quefarma_med_administracion":["T\u00f3pica"],"quefarma_med_venta":["Con receta"],"med_guias_enlaces_que_sirve":[""],"med_guias_enlaces_presentaciones":[""],"med_guias_enlaces_dosis":[""],"med_guias_enlaces_efectos":[""],"med_guias_enlaces_compara_precio":[""],"_yoast_wpseo_content_score":["90"],"med_doctor_resp":[""],"_thumbnail_id":["5094"],"_yoast_wpseo_focuskw":["Clobesol"],"_yoast_wpseo_linkdex":["78"],"med_riesgo_embarazo":["alto"],"med_riesgo_lactancia":["bajo"],"med_riesgo_alcohol":["bajo"],"quefarma_med_para_que_es":["Aliviar la comez\u00f3n"],"med_patente_generico":["patente"],"med_con_sin_receta":["con_receta"]}],"c":"dermatitis","md":[]}