{"p":"","i":"https://enviotodo.lacomuna.mx/wp-content/uploads/2019/09/0750132897916L2-125x125.jpg","pd":"09/07/2019","mdf":"09/07/2019","mt":[{"_edit_lock":["1569341453:18"],"_edit_last":["7"],"_yoast_wpseo_primary_category":["136"],"quefarma_med_tipo":["Medicamento gen\u00e9rico"],"quefarma_med_formula":["Fenobarbital"],"quefarma_med_presentaciones":["100 mg"],"quefarma_med_administracion":["Oral"],"quefarma_med_venta":["Con receta"],"med_doctor_resp":[""],"med_riesgo_embarazo":["alto"],"med_riesgo_lactancia":["medio"],"med_riesgo_alcohol":["alto"],"_yoast_wpseo_focuskw":["Fenobarbital"],"_yoast_wpseo_linkdex":["78"],"_yoast_wpseo_content_score":["60"],"_thumbnail_id":["7624"]}],"c":"ansiedad,dormir,esquizofrenia,Tratamientos Psiquiátricos","md":[]}