{"p":"132","i":"https://enviotodo.lacomuna.mx/wp-content/uploads/2019/09/propafenona-125x125.gif","pd":"10/14/2019","mdf":"10/14/2019","mt":[{"_edit_lock":["1571068648:7"],"_edit_last":["7"],"_yoast_wpseo_primary_category":["387"],"quefarma_med_tipo":["Medicamento Gen\u00e9rico"],"quefarma_med_formula":["Propafenona"],"quefarma_med_presentaciones":["150 mg\/300 mg"],"quefarma_med_administracion":["Oral"],"quefarma_med_venta":["Sin Receta"],"med_doctor_resp":[""],"med_riesgo_embarazo":["medio"],"med_riesgo_lactancia":["bajo"],"med_riesgo_alcohol":["medio"],"_yoast_wpseo_focuskw":["Propafenona"],"_yoast_wpseo_linkdex":["78"],"_yoast_wpseo_content_score":["60"],"_thumbnail_id":["7892"]}],"c":"arritmias,taquicardia","md":[]}