{"p":"175","i":"https://enviotodo.lacomuna.mx/wp-content/uploads/2019/09/sd-125x125.jpg","pd":"09/18/2019","mdf":"09/23/2019","mt":[{"_edit_lock":["1569209164:7"],"_edit_last":["7"],"_thumbnail_id":["7927"],"_yoast_wpseo_primary_category":["163"],"quefarma_med_tipo":["Medicamento de marca"],"quefarma_med_formula":["Loratadina"],"quefarma_med_presentaciones":["Cajas con 10 o 20 c\u00e1psulas de 10 mg | Frasco con 60 o 120 ml de jarabe de 100 mg | Frasco de 30 ml de soluci\u00f3n oral de 100 mg"],"quefarma_med_administracion":["Oral"],"quefarma_med_venta":["Con receta"],"med_doctor_resp":[""],"med_riesgo_embarazo":["alto"],"med_riesgo_lactancia":["bajo"],"med_riesgo_alcohol":["alto"],"_yoast_wpseo_content_score":["60"],"_yoast_wpseo_focuskw":["dimegan"],"_yoast_wpseo_linkdex":["78"]}],"c":"alergias en la piel,alergias respiratorias,conjuntivitis","md":[]}