{"p":"290","i":"https://enviotodo.lacomuna.mx/wp-content/uploads/2019/11/flixotide-1-125x125.png","pd":"11/19/2019","mdf":"11/19/2019","mt":[{"_edit_lock":["1574176907:7"],"_edit_last":["7"],"_thumbnail_id":["8703"],"_yoast_wpseo_primary_category":["117"],"quefarma_med_tipo":["Medicamento Patente"],"quefarma_med_formula":["Fluticasona"],"quefarma_med_presentaciones":["27 \u00b5g- 1 g\/ 10,2 g"],"quefarma_med_administracion":["Inhalatoria"],"quefarma_med_venta":["Con Receta"],"med_doctor_resp":[""],"med_riesgo_embarazo":["medio"],"med_riesgo_lactancia":["bajo"],"med_riesgo_alcohol":["bajo"],"_yoast_wpseo_focuskw":["Flixotide"],"_yoast_wpseo_linkdex":["78"],"_yoast_wpseo_content_score":["90"]}],"c":"asma,bronquitis,enfisema pulmonar,EPOC","md":[],"rl":[{"ID":10686,"post_title":"Mucovibrol C","post_name":"mucovibrol-c","post_parent":0},{"ID":10518,"post_title":"Sensibit","post_name":"sensibit","post_parent":0},{"ID":10461,"post_title":"Guayatetra","post_name":"guayatetra","post_parent":0},{"ID":10413,"post_title":"Broxol Plus","post_name":"broxol-plus","post_parent":0},{"ID":9644,"post_title":"Oxolvan","post_name":"oxolvan","post_parent":0},{"ID":9398,"post_title":"Sensemoc","post_name":"sensemoc","post_parent":0},{"ID":9491,"post_title":"Tetralisal","post_name":"tetralisal","post_parent":0},{"ID":9469,"post_title":"Histiacil Nf","post_name":"histiacil-nf","post_parent":0}]}